{"nodes": [{"course_id": "nbio405", "reg_prereqs": ["amath342"], "numCID": 405, "choice_prereqs": []}, {"course_id": "nbio404", "reg_prereqs": ["nbio401"], "numCID": 404, "choice_prereqs": []}, {"course_id": "nbio403", "reg_prereqs": ["nbio401"], "numCID": 403, "choice_prereqs": []}, {"course_id": "nbio402", "reg_prereqs": ["nbio401"], "numCID": 402, "choice_prereqs": []}, {"course_id": "nbio401", "reg_prereqs": ["nbio301"], "numCID": 401, "choice_prereqs": []}, {"course_id": "nbio450", "reg_prereqs": ["biol220"], "numCID": 450, "choice_prereqs": []}, {"course_id": "nbio440", "reg_prereqs": ["nbio302"], "numCID": 440, "choice_prereqs": []}, {"course_id": "nbio499", "reg_prereqs": ["nbio302"], "numCID": 499, "choice_prereqs": []}, {"course_id": "nbio301", "reg_prereqs": ["biol220"], "numCID": 301, "choice_prereqs": []}, {"course_id": "nbio302", "reg_prereqs": ["nbio301"], "numCID": 302, "choice_prereqs": []}, {"course_id": "nbio303", "reg_prereqs": ["math125"], "numCID": 303, "choice_prereqs": []}, {"course_id": "nbio490", "reg_prereqs": [], "numCID": 490, "choice_prereqs": []}, {"course_id": "nbio496", "reg_prereqs": [], "numCID": 496, "choice_prereqs": []}], "links": [{"source": 4, "target": 1}, {"source": 4, "target": 2}, {"source": 4, "target": 3}, {"source": 8, "target": 4}, {"source": 9, "target": 6}, {"source": 9, "target": 7}, {"source": 8, "target": 9}]}